gaussbock/__init__.py
gaussbock/gaussbock.py
gaussbock-1.0.9.dist-info/LICENSE
gaussbock-1.0.9.dist-info/METADATA
gaussbock-1.0.9.dist-info/WHEEL
gaussbock-1.0.9.dist-info/top_level.txt
gaussbock-1.0.9.dist-info/RECORD
