Metadata-Version: 2.1
Name: gaussbock
Version: 1.0.9
Summary: Fast parallel-iterative cosmological parameter estimation with Bayesian nonparametrics
Home-page: https://github.com/moews/gaussbock
Author: Ben Moews and Joe Zuntz
Author-email: ben.moews@protonmail.com
License: UNKNOWN
Keywords: astronomy,astrophysics,cosmology,bayesian,parameter estimation
Platform: UNKNOWN
Classifier: Programming Language :: Python :: 3 :: Only
Classifier: Intended Audience :: Science/Research
Classifier: License :: OSI Approved :: MIT License
Requires-Dist: numpy
Requires-Dist: emcee (>=2.0.0)
Requires-Dist: schwimmbad (>=0.3.0)
Requires-Dist: scikit-learn (>=0.18.1)
